geojsplit/__init__.py
geojsplit/cli.py
geojsplit/geojsplit.py
geojsplit-0.1.2.dist-info/entry_points.txt
geojsplit-0.1.2.dist-info/LICENSE
geojsplit-0.1.2.dist-info/WHEEL
geojsplit-0.1.2.dist-info/METADATA
geojsplit-0.1.2.dist-info/RECORD
