Metadata-Version: 2.1
Name: geojsplit
Version: 0.1.2
Summary: A python implementation of the npm package geojsplit. Used to split GeoJSON files into smaller pieces.
Home-page: https://github.com/underchemist/geojsplit
License: MIT
Keywords: geospatial,geojson,gis,python,stream
Author: Yann-Sebastien Tremblay-Johnston
Author-email: yanns.tremblay@gmail.com
Requires-Python: >=3.6,<4.0
Classifier: License :: OSI Approved :: MIT License
Classifier: Programming Language :: Python :: 3
Classifier: Programming Language :: Python :: 3.6
Classifier: Programming Language :: Python :: 3.7
Classifier: Topic :: Scientific/Engineering :: GIS
Classifier: Topic :: Utilities
Provides-Extra: docs
Requires-Dist: geojson (>=2.5,<3.0)
Requires-Dist: ijson (>=2.4,<3.0)
Requires-Dist: simplejson (>=3.16,<4.0)
Requires-Dist: sphinx (>=2.2,<3.0); extra == "docs"
Requires-Dist: sphinx_rtd_theme (>=0.4.3,<0.5.0); extra == "docs"
Project-URL: Documentation, https://geojsplit.readthedocs.io/en/latest/
Project-URL: Repository, https://github.com/underchemist/geojsplit
